{
 "version": "https://jsonfeed.org/version/1",
 "title": "Neds Corner Flora Survey Quadrat 0301",
 "description": "",
 "author": {
  "name": "chrisl",
  "url": "https://natureshare.org/items?i=https%3A%2F%2Ffiles.natureshare.org%2Fchrisl%2Fitems%2Findex.json"
 },
 "home_page_url": "https://natureshare.org/items?i=https%3A%2F%2Ffiles.natureshare.org%2Fchrisl%2Fcollections%2Fneds_corner_flora_survey_quadrat_0301%2Findex.json",
 "feed_url": "https://files.natureshare.org/chrisl/collections/neds_corner_flora_survey_quadrat_0301/index.json",
 "items": [
  {
   "id": "https://files.natureshare.org/chrisl/items/ns/2015/neds_corner_flora_survey_quadrat_0301_species_list.yaml",
   "url": "https://natureshare.org/item?i=https%3A%2F%2Ffiles.natureshare.org%2Fchrisl%2Fitems%2Fns%2F2015%2Fneds_corner_flora_survey_quadrat_0301_species_list.yaml",
   "title": "59 ids",
   "content_text": "Species list for collection.",
   "date_published": "2015-10-06T01:55:59.000+00:00",
   "date_modified": "2015-10-06T03:55:12.000+00:00",
   "tags": [
    "id~Actinobole uliginosum",
    "id~Alectryon oleifolius subsp. canescens",
    "id~Angianthus tomentosus",
    "id~Atriplex limbata",
    "id~Atriplex lindleyi",
    "id~Atriplex pumilio",
    "id~Austrostipa scabra subsp. falcata",
    "id~Brachyscome lineariloba",
    "id~Bromus rubens",
    "id~Bulbine semibarbata",
    "id~Calandrinia eremaea",
    "id~Calotis hispidula",
    "id~Chthonocephalus pseudevax",
    "id~Crassula colorata",
    "id~Crassula sieberiana s.l.",
    "id~Cucumis myriocarpus subsp. leptodermis",
    "id~Daucus glochidiatus",
    "id~Dysphania cristata",
    "id~Enchylaena tomentosa var. tomentosa",
    "id~Enneapogon avenaceus",
    "id~Eragrostis dielsii",
    "id~Euphorbia drummondii",
    "id~Herniaria cinerea",
    "id~Hordeum glaucum",
    "id~Hypochaeris radicata",
    "id~Lactuca spp.",
    "id~Lamarckia aurea",
    "id~Limonium lobatum",
    "id~Lycium australe",
    "id~Maireana pyramidata",
    "id~Maireana radiata",
    "id~Medicago minima",
    "id~Mesembryanthemum crystallinum",
    "id~Mesembryanthemum nodiflorum",
    "id~Nicotiana velutina",
    "id~Osteocarpum acropterum var. deminutum",
    "id~Osteocarpum salsuginosum",
    "id~Pimelea trichostachya",
    "id~Pogonolepis muelleriana",
    "id~Polycalymma stuartii",
    "id~Rhagodia spinescens",
    "id~Rhodanthe moschata",
    "id~Salsola tragus",
    "id~Sarcozona praecox",
    "id~Schismus barbatus",
    "id~Sclerochlamys brachyptera",
    "id~Sclerolaena diacantha",
    "id~Sclerolaena patenticuspis",
    "id~Sclerolaena tricuspis",
    "id~Senecio glossanthus s.l.",
    "id~Senecio pinnatifolius",
    "id~Sida corrugata",
    "id~Silene apetala var. apetala",
    "id~Sisymbrium orientale",
    "id~Sonchus oleraceus",
    "id~Tetragonia eremaea s.s.",
    "id~Vulpia myuros",
    "id~Wahlenbergia stricta subsp. stricta",
    "id~Wurmbea dioica",
    "tag~species-list"
   ],
   "_geo": {
    "coordinates": [
     141.29056,
     -34.12988
    ]
   },
   "_meta": {
    "date": "2015-10-06"
   },
   "author": {
    "name": "chrisl",
    "url": "https://natureshare.org/items?i=https%3A%2F%2Ffiles.natureshare.org%2Fchrisl%2Fitems%2Findex.json"
   }
  }
 ],
 "_meta": {
  "itemCount": 1,
  "pageNumber": 1,
  "pageCount": 1
 },
 "_display": {}
}